dummysensors/__init__.py
dummysensors/cli.py
dummysensors/config.py
dummysensors/io.py
dummysensors/orchestrator.py
dummysensors/registry.py
dummysensors/sensors.py
dummysensors/spec.py
dummysensors-0.3.2.dist-info/METADATA
dummysensors-0.3.2.dist-info/WHEEL
dummysensors-0.3.2.dist-info/entry_points.txt
dummysensors-0.3.2.dist-info/licenses/LICENSE
dummysensors-0.3.2.dist-info/RECORD
