Metadata-Version: 2.4
Name: dummysensors
Version: 0.3.2
Summary: Dummy sensor data generator for testing IoT/ML pipelines
Author: Mateusz Dalke
License: MIT
License-File: LICENSE
Requires-Python: >=3.9
Provides-Extra: config
Requires-Dist: pyyaml>=6.0; extra == 'config'
